pytest_reverse/__init__.py
pytest_reverse/py.typed
pytest_reverse-1.9.0.dist-info/licenses/LICENSE
pytest_reverse-1.9.0.dist-info/METADATA
pytest_reverse-1.9.0.dist-info/WHEEL
pytest_reverse-1.9.0.dist-info/entry_points.txt
pytest_reverse-1.9.0.dist-info/top_level.txt
pytest_reverse-1.9.0.dist-info/RECORD
